unifi/__init__.py
unifi/network.py
xorrkaz_unifi-1.0.0.dist-info/METADATA
xorrkaz_unifi-1.0.0.dist-info/WHEEL
xorrkaz_unifi-1.0.0.dist-info/top_level.txt
xorrkaz_unifi-1.0.0.dist-info/RECORD
