Metadata-Version: 2.1
Name: xorrkaz-unifi
Version: 1.0.0
Summary: Utilities for working with UniFi controllers
Author: Joe Clarke
Author-email: jclarke@marcuscom.com
License: MIT
Classifier: Intended Audience :: Developers
Classifier: License :: OSI Approved :: MIT License
Classifier: Programming Language :: Python :: 3.8
Requires-Python: >=3.8
